numpymongo/__init__.py
numpymongo/wrapper.py
numpymongo-0.1.dist-info/METADATA
numpymongo-0.1.dist-info/WHEEL
numpymongo-0.1.dist-info/top_level.txt
numpymongo-0.1.dist-info/RECORD
