Metadata-Version: 2.1
Name: numpymongo
Version: 0.1
Summary: A wrapper to export NumPy data to MongoDB
Home-page: https://github.com/manuel-lang/NumpyMongo
Author: Manuel Lang
Author-email: manuellang183@gmail.com
License: MIT
Platform: UNKNOWN
Requires-Dist: pymongo
Requires-Dist: numpy
